gabyte/__init__.py
gabyte-0.1.6.dist-info/METADATA
gabyte-0.1.6.dist-info/WHEEL
gabyte-0.1.6.dist-info/top_level.txt
gabyte-0.1.6.dist-info/RECORD
